auction_systems/__init__.py
auction_systems/auction_models.py
auction_systems/auction_sim.py
prisoners_dilemma/__init__.py
prisoners_dilemma/game.py
prisoners_dilemma/strategies.py
voting_systems/__init__.py
voting_systems/voting_models.py
voting_systems/voting_sim.py
stratepy-0.1.dist-info/LICENSE
stratepy-0.1.dist-info/METADATA
stratepy-0.1.dist-info/WHEEL
stratepy-0.1.dist-info/top_level.txt
stratepy-0.1.dist-info/RECORD
